<PAMDataset>
  <PAMRasterBand band="1">
    <Metadata>
      <MDI key="STATISTICS_MINIMUM">0.017004279858828</MDI>
      <MDI key="STATISTICS_MAXIMUM">143.24598756872</MDI>
      <MDI key="STATISTICS_MEAN">7.0338453830397</MDI>
      <MDI key="STATISTICS_STDDEV">6.0895993558553</MDI>
      <MDI key="STATISTICS_SKIPFACTORX">1</MDI>
      <MDI key="STATISTICS_SKIPFACTORY">1</MDI>
      <MDI key="STATISTICS_EXCLUDEDVALUES"></MDI>
      <MDI key="STATISTICS_COVARIANCES">37.0832203148333</MDI>
    </Metadata>
  </PAMRasterBand>
</PAMDataset>
