<PAMDataset>
  <PAMRasterBand band="1">
    <Metadata>
      <MDI key="STATISTICS_MINIMUM">0.024286322008193</MDI>
      <MDI key="STATISTICS_MAXIMUM">79.293851661021</MDI>
      <MDI key="STATISTICS_MEAN">7.9352681125578</MDI>
      <MDI key="STATISTICS_STDDEV">4.5856589396654</MDI>
      <MDI key="STATISTICS_SKIPFACTORX">1</MDI>
      <MDI key="STATISTICS_SKIPFACTORY">1</MDI>
      <MDI key="STATISTICS_EXCLUDEDVALUES"></MDI>
      <MDI key="STATISTICS_COVARIANCES">21.0282679109332</MDI>
    </Metadata>
  </PAMRasterBand>
</PAMDataset>
