<PAMDataset>
  <PAMRasterBand band="1">
    <Metadata>
      <MDI key="STATISTICS_MINIMUM">0.020190173299175</MDI>
      <MDI key="STATISTICS_MAXIMUM">78.436879342522</MDI>
      <MDI key="STATISTICS_MEAN">5.4053339145219</MDI>
      <MDI key="STATISTICS_STDDEV">4.5820191073593</MDI>
      <MDI key="STATISTICS_SKIPFACTORX">1</MDI>
      <MDI key="STATISTICS_SKIPFACTORY">1</MDI>
      <MDI key="STATISTICS_EXCLUDEDVALUES"></MDI>
      <MDI key="STATISTICS_COVARIANCES">20.994899100206</MDI>
    </Metadata>
  </PAMRasterBand>
</PAMDataset>
