<PAMDataset>
  <PAMRasterBand band="1">
    <Metadata>
      <MDI key="STATISTICS_MINIMUM">1</MDI>
      <MDI key="STATISTICS_MAXIMUM">128</MDI>
      <MDI key="STATISTICS_MEAN">15.633816455696</MDI>
      <MDI key="STATISTICS_STDDEV">19.611848869925</MDI>
      <MDI key="STATISTICS_SKIPFACTORX">1</MDI>
      <MDI key="STATISTICS_SKIPFACTORY">1</MDI>
      <MDI key="STATISTICS_EXCLUDEDVALUES"></MDI>
      <MDI key="STATISTICS_COVARIANCES">384.624616096793</MDI>
    </Metadata>
  </PAMRasterBand>
</PAMDataset>
