<PAMDataset>
  <PAMRasterBand band="1">
    <Metadata>
      <MDI key="STATISTICS_MINIMUM">1</MDI>
      <MDI key="STATISTICS_MAXIMUM">128</MDI>
      <MDI key="STATISTICS_MEAN">18.99764556962</MDI>
      <MDI key="STATISTICS_STDDEV">22.220998578567</MDI>
      <MDI key="STATISTICS_SKIPFACTORX">1</MDI>
      <MDI key="STATISTICS_SKIPFACTORY">1</MDI>
      <MDI key="STATISTICS_EXCLUDEDVALUES"></MDI>
      <MDI key="STATISTICS_COVARIANCES">493.772777828669</MDI>
    </Metadata>
  </PAMRasterBand>
</PAMDataset>
