<PAMDataset>
  <PAMRasterBand band="1">
    <Metadata>
      <MDI key="STATISTICS_MINIMUM">0.010289217038097</MDI>
      <MDI key="STATISTICS_MAXIMUM">359.95982992082</MDI>
      <MDI key="STATISTICS_MEAN">216.81051563739</MDI>
      <MDI key="STATISTICS_STDDEV">74.352384576317</MDI>
      <MDI key="STATISTICS_SKIPFACTORX">1</MDI>
      <MDI key="STATISTICS_SKIPFACTORY">1</MDI>
      <MDI key="STATISTICS_EXCLUDEDVALUES"></MDI>
      <MDI key="STATISTICS_COVARIANCES">5528.27709218448</MDI>
    </Metadata>
  </PAMRasterBand>
</PAMDataset>
