<PAMDataset>
  <PAMRasterBand band="1">
    <Metadata>
      <MDI key="STATISTICS_MINIMUM">0.0073091401816924</MDI>
      <MDI key="STATISTICS_MAXIMUM">359.96001736827</MDI>
      <MDI key="STATISTICS_MEAN">210.58549030789</MDI>
      <MDI key="STATISTICS_STDDEV">67.664590075279</MDI>
      <MDI key="STATISTICS_SKIPFACTORX">1</MDI>
      <MDI key="STATISTICS_SKIPFACTORY">1</MDI>
      <MDI key="STATISTICS_EXCLUDEDVALUES"></MDI>
      <MDI key="STATISTICS_COVARIANCES">4578.49675005552</MDI>
    </Metadata>
  </PAMRasterBand>
</PAMDataset>
