<PAMDataset>
  <PAMRasterBand band="1">
    <Metadata>
      <MDI key="STATISTICS_MINIMUM">0.0069312564774909</MDI>
      <MDI key="STATISTICS_MAXIMUM">359.97899104715</MDI>
      <MDI key="STATISTICS_MEAN">203.7125366709</MDI>
      <MDI key="STATISTICS_STDDEV">66.781903445707</MDI>
      <MDI key="STATISTICS_SKIPFACTORX">1</MDI>
      <MDI key="STATISTICS_SKIPFACTORY">1</MDI>
      <MDI key="STATISTICS_EXCLUDEDVALUES"></MDI>
      <MDI key="STATISTICS_COVARIANCES">4459.82262783168</MDI>
    </Metadata>
  </PAMRasterBand>
</PAMDataset>
