<PAMDataset>
  <PAMRasterBand band="1">
    <Metadata>
      <MDI key="STATISTICS_MINIMUM">0.001006981548999</MDI>
      <MDI key="STATISTICS_MAXIMUM">359.97666395521</MDI>
      <MDI key="STATISTICS_MEAN">217.39866137063</MDI>
      <MDI key="STATISTICS_STDDEV">78.034223593383</MDI>
      <MDI key="STATISTICS_SKIPFACTORX">1</MDI>
      <MDI key="STATISTICS_SKIPFACTORY">1</MDI>
      <MDI key="STATISTICS_EXCLUDEDVALUES"></MDI>
      <MDI key="STATISTICS_COVARIANCES">6089.34005182204</MDI>
    </Metadata>
  </PAMRasterBand>
</PAMDataset>
