<PAMDataset>
  <PAMRasterBand band="1">
    <Metadata>
      <MDI key="STATISTICS_MINIMUM">0.010542052165149</MDI>
      <MDI key="STATISTICS_MAXIMUM">359.97217622508</MDI>
      <MDI key="STATISTICS_MEAN">204.72458966851</MDI>
      <MDI key="STATISTICS_STDDEV">72.226099510343</MDI>
      <MDI key="STATISTICS_SKIPFACTORX">1</MDI>
      <MDI key="STATISTICS_SKIPFACTORY">1</MDI>
      <MDI key="STATISTICS_EXCLUDEDVALUES"></MDI>
      <MDI key="STATISTICS_COVARIANCES">5216.60945047799</MDI>
    </Metadata>
  </PAMRasterBand>
</PAMDataset>
